[
    {
        "nome": "prova",
        "numGiocatori": 3,
        "codice": 7799,
        "statoPartita": "Sospesa",
        "accessi": [
            "pupo",
            "pupa"
        ],
        "partecipanti": [
            {
                "nome": "pupo",
                "carteTotaliPescate": 0,
                "puntiTotaliFatti": 0,
                "bombettePescate": 0,
                "partiteGiocate": 0,
                "vittorie": 0,
                "bot": false
            },
            {
                "nome": "pupa",
                "carteTotaliPescate": 0,
                "puntiTotaliFatti": 0,
                "bombettePescate": 0,
                "partiteGiocate": 0,
                "vittorie": 0,
                "bot": false
            },
            {
                "nome": "Bot-1",
                "carteTotaliPescate": 0,
                "puntiTotaliFatti": 0,
                "bombettePescate": 0,
                "partiteGiocate": 0,
                "vittorie": 0,
                "bot": true
            }
        ]
    },
    {
        "nome": "èropva",
        "numGiocatori": 3,
        "codice": 1947,
        "statoPartita": "Sospesa",
        "accessi": [
            "pupa",
            "pupo"
        ],
        "partecipanti": [
            {
                "nome": "pupa",
                "carteTotaliPescate": 0,
                "puntiTotaliFatti": 0,
                "bombettePescate": 0,
                "partiteGiocate": 0,
                "vittorie": 0,
                "bot": false
            },
            {
                "nome": "pupo",
                "carteTotaliPescate": 0,
                "puntiTotaliFatti": 0,
                "bombettePescate": 0,
                "partiteGiocate": 0,
                "vittorie": 0,
                "bot": false
            },
            {
                "nome": "Bot-1",
                "carteTotaliPescate": 0,
                "puntiTotaliFatti": 0,
                "bombettePescate": 0,
                "partiteGiocate": 0,
                "vittorie": 0,
                "bot": true
            }
        ]
    },
    {
        "nome": "èrova",
        "numGiocatori": 3,
        "codice": 4564,
        "statoPartita": "Pronta",
        "accessi": [
            "pupa",
            "pupo"
        ],
        "partecipanti": [
            {
                "nome": "pupa",
                "carteTotaliPescate": 0,
                "puntiTotaliFatti": 0,
                "bombettePescate": 0,
                "partiteGiocate": 0,
                "vittorie": 0,
                "bot": false
            },
            {
                "nome": "pupo",
                "carteTotaliPescate": 0,
                "puntiTotaliFatti": 0,
                "bombettePescate": 0,
                "partiteGiocate": 0,
                "vittorie": 0,
                "bot": false
            },
            {
                "nome": "Bot-1",
                "carteTotaliPescate": 0,
                "puntiTotaliFatti": 0,
                "bombettePescate": 0,
                "partiteGiocate": 0,
                "vittorie": 0,
                "bot": true
            }
        ]
    }
]