["java.util.ArrayList",[["com.example.GestioneTornei.Torneo",{"nomeTorneo":"fwqd","numGiocatori":4,"codice":2799,"statoTorneo":"Terminato","partite":["[Lcom.example.GestionePartite.Partita;",[["com.example.GestionePartite.Partita",{"nome":"Partita0","numGiocatori":2,"codice":2799,"vincitore":["com.example.GestioneGiocatori.Giocatore",{"nome":"pupi","carteTotaliPescate":2,"puntiTotaliFatti":0,"bombettePescate":0,"partiteGiocate":2,"vittorie":2,"vittorieTorneo":2,"vincitore":true}],"statoPartita":"Terminata","accessi":["java.util.ArrayList",[]],"partecipanti":["java.util.ArrayList",[["com.example.GestioneGiocatori.Giocatore",{"nome":"pupi","carteTotaliPescate":2,"puntiTotaliFatti":0,"bombettePescate":0,"partiteGiocate":2,"vittorie":2,"vittorieTorneo":2,"vincitore":true}],["com.example.GestioneGiocatori.Giocatore",{"nome":"pupo","carteTotaliPescate":0,"puntiTotaliFatti":0,"bombettePescate":0,"partiteGiocate":1,"vittorie":0,"vittorieTorneo":0,"vincitore":false}]]]}],["com.example.GestionePartite.Partita",{"nome":"Partita1","numGiocatori":2,"codice":2799,"vincitore":["com.example.GestioneGiocatori.Giocatore",{"nome":"pupe","carteTotaliPescate":2,"puntiTotaliFatti":0,"bombettePescate":0,"partiteGiocate":2,"vittorie":1,"vittorieTorneo":0,"vincitore":false}],"statoPartita":"Terminata","accessi":["java.util.ArrayList",[]],"partecipanti":["java.util.ArrayList",[["com.example.GestioneGiocatori.Giocatore",{"nome":"pupe","carteTotaliPescate":2,"puntiTotaliFatti":0,"bombettePescate":0,"partiteGiocate":2,"vittorie":1,"vittorieTorneo":0,"vincitore":false}],["com.example.GestioneGiocatori.Giocatore",{"nome":"pupa","carteTotaliPescate":0,"puntiTotaliFatti":0,"bombettePescate":0,"partiteGiocate":1,"vittorie":0,"vittorieTorneo":0,"vincitore":false}]]]}],["com.example.GestionePartite.Partita",{"nome":"Partita2","numGiocatori":2,"codice":2799,"vincitore":["com.example.GestioneGiocatori.Giocatore",{"nome":"pupi","carteTotaliPescate":2,"puntiTotaliFatti":0,"bombettePescate":0,"partiteGiocate":2,"vittorie":2,"vittorieTorneo":2,"vincitore":true}],"statoPartita":"Terminata","accessi":["java.util.ArrayList",[]],"partecipanti":["java.util.ArrayList",[["com.example.GestioneGiocatori.Giocatore",{"nome":"pupi","carteTotaliPescate":2,"puntiTotaliFatti":0,"bombettePescate":0,"partiteGiocate":2,"vittorie":2,"vittorieTorneo":2,"vincitore":true}],["com.example.GestioneGiocatori.Giocatore",{"nome":"pupe","carteTotaliPescate":2,"puntiTotaliFatti":0,"bombettePescate":0,"partiteGiocate":2,"vittorie":1,"vittorieTorneo":0,"vincitore":false}]]]}]]],"accessi":["java.util.ArrayList",["pupa","pupo","pupe","pupi"]],"partecipanti":["java.util.ArrayList",[]]}]]]